PyRVCTestG.cp37-win_amd64.pyd
PyRVCTestG.pdb
PyRVCTestF-1.7.0.dist-info/METADATA
PyRVCTestF-1.7.0.dist-info/WHEEL
PyRVCTestF-1.7.0.dist-info/top_level.txt
PyRVCTestF-1.7.0.dist-info/RECORD
